<annotation>
	<folder>9</folder>
	<filename>img_01_4402270500_00003.jpg</filename>
	<path>E:\002_Data\suface dectect\2-fuxinzhe\msos1\9\img_01_4402270500_00003.jpg</path>
	<source>
		<database>Unknown</database>
	</source>
	<size>
		<width>2048</width>
		<height>1000</height>
		<depth>1</depth>
	</size>
	<segmented>0</segmented>
	<object>
		<name>9_zhehen</name>
		<pose>Unspecified</pose>
		<truncated>0</truncated>
		<difficult>0</difficult>
		<bndbox>
			<xmin>491</xmin>
			<ymin>262</ymin>
			<xmax>2029</xmax>
			<ymax>347</ymax>
		</bndbox>
	</object>
	<object>
		<name>9_zhehen</name>
		<pose>Unspecified</pose>
		<truncated>0</truncated>
		<difficult>0</difficult>
		<bndbox>
			<xmin>788</xmin>
			<ymin>608</ymin>
			<xmax>1083</xmax>
			<ymax>667</ymax>
		</bndbox>
	</object>
	<object>
		<name>9_zhehen</name>
		<pose>Unspecified</pose>
		<truncated>0</truncated>
		<difficult>0</difficult>
		<bndbox>
			<xmin>489</xmin>
			<ymin>603</ymin>
			<xmax>637</xmax>
			<ymax>643</ymax>
		</bndbox>
	</object>
	<object>
		<name>9_zhehen</name>
		<pose>Unspecified</pose>
		<truncated>0</truncated>
		<difficult>0</difficult>
		<bndbox>
			<xmin>642</xmin>
			<ymin>547</ymin>
			<xmax>845</xmax>
			<ymax>582</ymax>
		</bndbox>
	</object>
	<object>
		<name>9_zhehen</name>
		<pose>Unspecified</pose>
		<truncated>0</truncated>
		<difficult>0</difficult>
		<bndbox>
			<xmin>942</xmin>
			<ymin>693</ymin>
			<xmax>1042</xmax>
			<ymax>827</ymax>
		</bndbox>
	</object>
	<object>
		<name>9_zhehen</name>
		<pose>Unspecified</pose>
		<truncated>0</truncated>
		<difficult>0</difficult>
		<bndbox>
			<xmin>961</xmin>
			<ymin>159</ymin>
			<xmax>1010</xmax>
			<ymax>213</ymax>
		</bndbox>
	</object>
</annotation>
