<annotation>
	<folder>5</folder>
	<filename>img_03_3402617700_00783.jpg</filename>
	<path>E:\002_Data\suface dectect\2-fuxinzhe\msos1\5\img_03_3402617700_00783.jpg</path>
	<source>
		<database>Unknown</database>
	</source>
	<size>
		<width>2048</width>
		<height>1000</height>
		<depth>1</depth>
	</size>
	<segmented>0</segmented>
	<object>
		<name>5_youban</name>
		<pose>Unspecified</pose>
		<truncated>0</truncated>
		<difficult>0</difficult>
		<bndbox>
			<xmin>1581</xmin>
			<ymin>51</ymin>
			<xmax>1861</xmax>
			<ymax>341</ymax>
		</bndbox>
	</object>
</annotation>
